LICENSE
README.md
pyproject.toml
src/kgen/__init__.py
src/kgen/formatter.py
src/kgen/generate.py
src/kgen/logging.py
src/kgen/metainfo.py
src/kgen/models.py
src/kgen/patch.py
src/kgen/utils.py
src/kgen/executor/__init__.py
src/kgen/executor/dtg.py
src/kgen/executor/tipo.py
src/kgen/sampling/__init__.py
src/kgen/sampling/beam.py
src/kgen/sampling/cg_mcts.py
src/kgen/sampling/node_splitters.py
src/kgen/sampling/rw_mcts.py
src/kgen/tag-list/__init__.py
src/kgen/tag-list/artist.txt
src/kgen/tag-list/characters.txt
src/kgen/tag-list/copyrights.txt
src/kgen/tag-list/meta.txt
src/kgen_exp/__init__.py
src/kgen_exp/diff.py
src/kgen_exp/img_utils.py
src/kgen_exp/meta.py
src/kgen_exp/metrics/__init__.py
src/kgen_exp/metrics/aesthetic.py
src/kgen_exp/metrics/aicorrupt.py
src/kgen_exp/metrics/base.py
src/kgen_exp/metrics/clip.py
src/kgen_exp/metrics/fd_text.py
src/kgen_exp/metrics/fid.py
src/kgen_exp/metrics/vendi.py
src/kgen_exp/metrics/vendi_text.py
src/tipo_kgen.egg-info/PKG-INFO
src/tipo_kgen.egg-info/SOURCES.txt
src/tipo_kgen.egg-info/dependency_links.txt
src/tipo_kgen.egg-info/requires.txt
src/tipo_kgen.egg-info/top_level.txt