Metadata-Version: 2.1
Name: tipo-kgen
Version: 0.1.6
Summary: TIPO: Text to Image with text Presampling for Optimal prompting
Author-email: "Shih-Ying Yeh(KohakuBlueLeaf)" <apolloyeh0123@gmail.com>
License: Apache-2.0
Project-URL: Homepage, https://github.com/KohakuBlueleaf/KGen
Requires-Python: >=3.10
License-File: LICENSE
Requires-Dist: transformers
Requires-Dist: huggingface_hub
Requires-Dist: torch
Provides-Extra: dev
Requires-Dist: orjson; extra == "dev"
Requires-Dist: orjsonl; extra == "dev"
Requires-Dist: torchmetrics; extra == "dev"
Requires-Dist: vendi_score; extra == "dev"
Requires-Dist: k_diffusion; extra == "dev"
